openpy_ts_clu/__init__.py
openpy_ts_clu/BBDD/__init__.py
openpy_ts_clu/BBDD/dataset_imputation_30min.csv
openpy_ts_clu/BBDD/load_example.py
openpy_ts_clu/clustering_algorithm.py
openpy_ts_clu/data_preprocessing.py
openpy_ts_clu/prepare_data.py
openpy_ts_clu/utils.py
openpy_ts_clu/utils_plot.py
openpy_ts_clu-0.1.1.dist-info/METADATA
openpy_ts_clu-0.1.1.dist-info/WHEEL
openpy_ts_clu-0.1.1.dist-info/RECORD
